sqlite_easy_ctrl/__init__.py
sqlite_easy_ctrl-0.1.2.dist-info/LICENSE
sqlite_easy_ctrl-0.1.2.dist-info/METADATA
sqlite_easy_ctrl-0.1.2.dist-info/WHEEL
sqlite_easy_ctrl-0.1.2.dist-info/top_level.txt
sqlite_easy_ctrl-0.1.2.dist-info/RECORD
