Metadata-Version: 2.1
Name: sqlite_easy_ctrl
Version: 0.1.2
Summary: 一个可以更方便的操作SQLite数据的Python库
Home-page: https://github.com/xingchentye/Python-Sqlite3-EasyCtrl
Author: xingchen
Author-email: xingchenawa@qq.com
Classifier: Programming Language :: Python :: 3
Classifier: License :: OSI Approved :: BSD License
Classifier: Operating System :: OS Independent
Requires-Python: >=3.6
License-File: LICENSE
